easymodels/__init__.py
easymodels/__main__.py
easymodels/utils/__init__.py
easymodels/utils/categories.py
easymodels/utils/constants.py
easymodels/utils/gui.py
easymodels/utils/menu.py
EasyModels-1.6.2.dist-info/LICENSE
EasyModels-1.6.2.dist-info/METADATA
EasyModels-1.6.2.dist-info/WHEEL
EasyModels-1.6.2.dist-info/entry_points.txt
EasyModels-1.6.2.dist-info/top_level.txt
EasyModels-1.6.2.dist-info/RECORD
