Metadata-Version: 2.1
Name: EasyModels
Version: 1.6.2
Summary: Command Line User Interface for finding pre-trained AI models
Home-page: https://github.com/M4cs/EasyModels
Author: Max Bridgland
Author-email: mabridgland@protonmail.com
License: UNKNOWN
Keywords: AI,tensorflow,models,training,pre-train,pre-trained,artifical intelligence,keras,YOLO,opencv,pytorch,chainer,easymodels,ezmodels
Platform: UNKNOWN
Classifier: Programming Language :: Python :: 3
Classifier: Programming Language :: Python :: 3.4
Classifier: Programming Language :: Python :: 3.5
Classifier: Programming Language :: Python :: 3.6
Classifier: Programming Language :: Python :: 3.7
Classifier: Topic :: Multimedia :: Graphics
Classifier: Operating System :: OS Independent
Requires-Dist: requests (>=2.21.0)
Requires-Dist: terminaltables (>=3.1.0)
Requires-Dist: PySimpleGUIQt (>=0.26.0)
Requires-Dist: PySide2 (>=5.13.0)
Requires-Dist: crayons (>=0.2.0)
Requires-Dist: tqdm (==4.33.0)
